wods/__init__.py
wods-0.0.1.dist-info/licenses/LICENSE
wods-0.0.1.dist-info/METADATA
wods-0.0.1.dist-info/WHEEL
wods-0.0.1.dist-info/top_level.txt
wods-0.0.1.dist-info/RECORD
