Metadata-Version: 2.4
Name: wods
Version: 0.0.1
Summary: wods
License: Copyright (c) <year> <copyright holders>
Keywords: development
Classifier: Development Status :: 3 - Alpha
Classifier: Intended Audience :: Developers
Classifier: License :: OSI Approved :: MIT License
Requires-Python: >=3.7
License-File: LICENSE
Dynamic: license-file
